{
  "aarch64-linux": {
    "url": "https://nodejs.org/dist/v4.6.0/node-v4.6.0-linux-arm64.tar.xz",
    "sha256": "sha256-doPmZLZIxOw/hpNfS0+fv1bxnRceHinVrfaH/Ew5K1s="
  },
  "x86_64-linux": {
    "url": "https://nodejs.org/dist/v4.6.0/node-v4.6.0-linux-x64.tar.xz",
    "sha256": "sha256-p3zrdaBZhBUzBK0PCbEdI0ylSmdxS6V1tS5CmN8DQ9E="
  },
  "x86_64-darwin": {
    "url": "https://nodejs.org/dist/v4.6.0/node-v4.6.0-darwin-x64.tar.xz",
    "sha256": "sha256-PHKMJbVB/YuIgmVo54ZwmGWN98RdI4m2CHfAk6mAO9A="
  },
  "aarch64-darwin": null,
  "release_type": "lts"
}
